realpath/__init__.py
realpath-0.1.0.dist-info/LICENSE
realpath-0.1.0.dist-info/WHEEL
realpath-0.1.0.dist-info/METADATA
realpath-0.1.0.dist-info/RECORD
